mldoe/__init__.py
mldoe/design.py
mldoe/enumeration.py
mldoe/matrix.py
mldoe/tools.py
mldoe/wlp.py
mldoe-0.0.5.dist-info/LICENSE
mldoe-0.0.5.dist-info/METADATA
mldoe-0.0.5.dist-info/WHEEL
mldoe-0.0.5.dist-info/top_level.txt
mldoe-0.0.5.dist-info/RECORD
