Metadata-Version: 2.1
Name: mldoe
Version: 0.0.5
Summary: Tools to create and characterize regular mixed-level designs
Home-page: https://github.com/ABohynDOE/mldoe
Author: Alexandre Bohyn
Author-email: alexandre.bohyn@kuleuven.be
License: UNKNOWN
Keywords: doe,design,mixed-level,regular
Platform: UNKNOWN
Classifier: Development Status :: 3 - Alpha
Classifier: Programming Language :: Python :: 3
Classifier: License :: OSI Approved :: MIT License
Classifier: Operating System :: OS Independent
Requires-Python: >=3.7
